{
  "experiment_id": "20260329_transformer_300",
  "trial_id": "20260329_transformer_300_053",
  "model_class": "Transformer",
  "champion_eligible": true,
  "description": "Transformer lookback=8 model_dim=16 num_heads=2 num_layers=1 feedforward_dim=32 epochs=75 learning_rate=0.01 with real_gdp",
  "gof_composite": 0.2530290171357927,
  "gof_insample": 0.23232162118576516,
  "gof_validation_near": 0.35255459399584,
  "gof_validation_far": 0.022486182864061677,
  "gof_diagnostic": 0.3333333333333333,
  "rmse": 23.59116480472986,
  "mae": 19.675346547444665,
  "theil_u": 0.64744540600416,
  "directional_accuracy": 0.5864661654135338,
  "n_params": 8,
  "status": "ok",
  "diagnostics_passed": [
    "adf",
    "forecast_plausibility"
  ],
  "diagnostics_failed": [
    "ljung_box",
    "jarque_bera",
    "arch_lm",
    "cusum"
  ],
  "error_summary": "",
  "rmse_1yr": 23.59116480472986,
  "rmse_3yr": 112.1239427401415,
  "insample_rmse": 5.123073816502296,
  "naive_insample_rmse": 6.6734637289322345,
  "gof_volatility_near": NaN,
  "gof_volatility_far": NaN,
  "gof_volatility_weighted": NaN,
  "validation_coverage_90": NaN,
  "fit_attempts": [],
  "fit_strategy": "",
  "fit_scaled": false,
  "fit_recovered": false
}