{
  "experiment_id": "20260329_gradient_boosting_300",
  "trial_id": "20260329_gradient_boosting_300_099",
  "model_class": "Gradient Boosting",
  "champion_eligible": true,
  "description": "Gradient Boosting n_estimators=200 learning_rate=0.03 max_depth=3 min_samples_leaf=1 lags=[1, 4, 8] with mortgage_rate",
  "gof_composite": 0.44708343213289076,
  "gof_insample": 0.7845347792631222,
  "gof_validation_near": 0.24242460265957144,
  "gof_validation_far": -0.010527270021387647,
  "gof_diagnostic": 0.5,
  "rmse": 27.604004731407304,
  "mae": 22.88365017971224,
  "theil_u": 0.7575753973404286,
  "directional_accuracy": 0.16040100250626566,
  "n_params": 9,
  "status": "ok",
  "diagnostics_passed": [
    "arch_lm",
    "adf",
    "forecast_plausibility"
  ],
  "diagnostics_failed": [
    "ljung_box",
    "jarque_bera",
    "cusum"
  ],
  "error_summary": "",
  "rmse_1yr": 27.604004731407304,
  "rmse_3yr": 115.91069074931845,
  "insample_rmse": 1.4378993354339313,
  "naive_insample_rmse": 6.6734637289322345,
  "gof_volatility_near": NaN,
  "gof_volatility_far": NaN,
  "gof_volatility_weighted": NaN,
  "validation_coverage_90": NaN,
  "fit_attempts": [],
  "fit_strategy": "",
  "fit_scaled": false,
  "fit_recovered": false
}