{
  "experiment_id": "20260325_threshold_var_refine_20",
  "trial_id": "20260325_threshold_var_refine_20_016",
  "model_class": "Threshold VAR / SETAR",
  "champion_eligible": true,
  "description": "Threshold VAR(1) delay=1 q=0.45 threshold=term_spread with mortgage_rate, term_spread",
  "gof_composite": -0.7009710684156258,
  "gof_insample": 0.1402697237570104,
  "gof_validation_near": -0.8634827026680476,
  "gof_validation_far": -3.032400079897423,
  "gof_diagnostic": 0.0,
  "rmse": 67.90028493788225,
  "mae": 54.35494061271979,
  "theil_u": 1.8634827026680476,
  "directional_accuracy": 0.5939849624060151,
  "n_params": 27,
  "status": "ok",
  "diagnostics_passed": [],
  "diagnostics_failed": [
    "ljung_box",
    "jarque_bera",
    "arch_lm",
    "cusum",
    "adf",
    "forecast_plausibility"
  ],
  "error_summary": "",
  "rmse_1yr": 67.90028493788225,
  "rmse_3yr": 462.52910980682867,
  "insample_rmse": 5.737378815172481,
  "naive_insample_rmse": 6.6734637289322345,
  "gof_volatility_near": NaN,
  "gof_volatility_far": NaN,
  "gof_volatility_weighted": NaN,
  "validation_coverage_90": NaN,
  "fit_attempts": [],
  "fit_strategy": "",
  "fit_scaled": false,
  "fit_recovered": false
}