{
  "experiment_id": "20260331_dynamic_factor_full20_300",
  "trial_id": "20260331_dynamic_factor_full20_300_020",
  "model_class": "Dynamic Factor",
  "champion_eligible": true,
  "description": "Dynamic Factor(k_factors=1, factor_order=2) with personal_consumption",
  "gof_composite": -2.7612946375050673,
  "gof_insample": -2.8623561138077935,
  "gof_validation_near": -3.716945120377642,
  "gof_validation_far": -2.3250315545540565,
  "gof_diagnostic": 0.3333333333333333,
  "rmse": 171.87276128264054,
  "mae": 159.76499009893328,
  "theil_u": 4.716945120377642,
  "directional_accuracy": 0.17794486215538846,
  "n_params": 6,
  "status": "ok",
  "diagnostics_passed": [
    "adf",
    "forecast_plausibility"
  ],
  "diagnostics_failed": [
    "ljung_box",
    "jarque_bera",
    "arch_lm",
    "cusum"
  ],
  "error_summary": "",
  "rmse_1yr": 171.87276128264054,
  "rmse_3yr": 381.391690937231,
  "insample_rmse": 25.775293433715973,
  "naive_insample_rmse": 6.6734637289322345,
  "gof_volatility_near": NaN,
  "gof_volatility_far": NaN,
  "gof_volatility_weighted": NaN,
  "validation_coverage_90": NaN,
  "fit_attempts": [
    {
      "attempt": 1,
      "name": "baseline_lbfgs",
      "method": "lbfgs",
      "maxiter": 200,
      "scale_inputs": false,
      "enforce_stationarity": true,
      "status": "ok",
      "optimizer_converged": true,
      "warnings": []
    }
  ],
  "fit_strategy": "baseline_lbfgs",
  "fit_scaled": false,
  "fit_recovered": false
}