{
  "experiment_id": "20260329_gradient_boosting_300",
  "trial_id": "20260329_gradient_boosting_300_076",
  "model_class": "Gradient Boosting",
  "champion_eligible": true,
  "description": "Gradient Boosting n_estimators=200 learning_rate=0.03 max_depth=3 min_samples_leaf=4 lags=[1, 2, 4] with mortgage_rate",
  "gof_composite": 0.3956478839920593,
  "gof_insample": 0.7208130096527654,
  "gof_validation_near": 0.22172391917788847,
  "gof_validation_far": -0.024093499430940746,
  "gof_diagnostic": 0.3333333333333333,
  "rmse": 28.35828181957278,
  "mae": 23.747165560072975,
  "theil_u": 0.7782760808221115,
  "directional_accuracy": 0.16290726817042606,
  "n_params": 9,
  "status": "ok",
  "diagnostics_passed": [
    "adf",
    "forecast_plausibility"
  ],
  "diagnostics_failed": [
    "ljung_box",
    "jarque_bera",
    "arch_lm",
    "cusum"
  ],
  "error_summary": "",
  "rmse_1yr": 28.35828181957278,
  "rmse_3yr": 117.46678039516416,
  "insample_rmse": 1.8631442536720237,
  "naive_insample_rmse": 6.6734637289322345,
  "gof_volatility_near": NaN,
  "gof_volatility_far": NaN,
  "gof_volatility_weighted": NaN,
  "validation_coverage_90": NaN,
  "fit_attempts": [],
  "fit_strategy": "",
  "fit_scaled": false,
  "fit_recovered": false
}