{
  "experiment_id": "20260330_ardl_full20_300",
  "trial_id": "20260330_ardl_full20_300_007",
  "model_class": "ARDL",
  "champion_eligible": true,
  "description": "ARDL(ar_lags=2, distributed_lags=1) trend=c with no exogenous variables",
  "gof_composite": -6.133469333708713e+16,
  "gof_insample": 0.27956126006205406,
  "gof_validation_near": -545871.5553286992,
  "gof_validation_far": -4.0889795557930714e+17,
  "gof_diagnostic": 0.5,
  "rmse": 19890124.01001671,
  "mae": 7678227.092738187,
  "theil_u": 545872.5553286992,
  "directional_accuracy": 0.8220551378446115,
  "n_params": 3,
  "status": "ok",
  "diagnostics_passed": [
    "cusum",
    "adf",
    "forecast_plausibility"
  ],
  "diagnostics_failed": [
    "ljung_box",
    "jarque_bera",
    "arch_lm"
  ],
  "error_summary": "",
  "rmse_1yr": 19890124.01001671,
  "rmse_3yr": 4.6901895558126305e+19,
  "insample_rmse": 4.807821799893525,
  "naive_insample_rmse": 6.6734637289322345,
  "gof_volatility_near": NaN,
  "gof_volatility_far": NaN,
  "gof_volatility_weighted": NaN,
  "validation_coverage_90": NaN,
  "fit_attempts": [],
  "fit_strategy": "",
  "fit_scaled": false,
  "fit_recovered": false
}