{
  "experiment_id": "20260331_dynamic_factor_full20_300",
  "trial_id": "20260331_dynamic_factor_full20_300_033",
  "model_class": "Dynamic Factor",
  "champion_eligible": true,
  "description": "Dynamic Factor(k_factors=1, factor_order=4) with consumer_confidence, mortgage_rate",
  "gof_composite": -Infinity,
  "gof_insample": -55.404270904299246,
  "gof_validation_near": -2.5057759114139262e+107,
  "gof_validation_far": -Infinity,
  "gof_diagnostic": 0.0,
  "rmse": 9.13037175670504e+108,
  "mae": 8.553114936993301e+107,
  "theil_u": 2.5057759114139262e+107,
  "directional_accuracy": 0.2807017543859649,
  "n_params": 10,
  "status": "ok",
  "diagnostics_passed": [],
  "diagnostics_failed": [
    "ljung_box",
    "jarque_bera",
    "arch_lm",
    "cusum",
    "adf",
    "forecast_plausibility"
  ],
  "error_summary": "",
  "rmse_1yr": 9.13037175670504e+108,
  "rmse_3yr": Infinity,
  "insample_rmse": 376.4118560367088,
  "naive_insample_rmse": 6.6734637289322345,
  "gof_volatility_near": NaN,
  "gof_volatility_far": NaN,
  "gof_volatility_weighted": NaN,
  "validation_coverage_90": NaN,
  "fit_attempts": [
    {
      "attempt": 1,
      "name": "baseline_lbfgs",
      "method": "lbfgs",
      "maxiter": 200,
      "scale_inputs": false,
      "enforce_stationarity": true,
      "status": "exception",
      "exception": "LU decomposition error."
    },
    {
      "attempt": 2,
      "name": "relaxed_lbfgs",
      "method": "lbfgs",
      "maxiter": 200,
      "scale_inputs": false,
      "enforce_stationarity": false,
      "status": "ok",
      "optimizer_converged": true,
      "warnings": []
    }
  ],
  "fit_strategy": "relaxed_lbfgs",
  "fit_scaled": false,
  "fit_recovered": true
}