{
  "experiment_id": "20260325_dynamic_factor_60_stable",
  "trial_id": "20260325_dynamic_factor_60_stable_044",
  "model_class": "Dynamic Factor",
  "champion_eligible": true,
  "description": "Dynamic Factor(k_factors=1, factor_order=2) with mortgage_rate, housing_inventory",
  "gof_composite": -23.797733287705896,
  "gof_insample": -55.404270904299246,
  "gof_validation_near": -3.8778445418298215,
  "gof_validation_far": -1.8585289089717065,
  "gof_diagnostic": 0.0,
  "rmse": 177.73550234661786,
  "mae": 130.61154016243873,
  "theil_u": 4.8778445418298215,
  "directional_accuracy": 0.14536340852130325,
  "n_params": 8,
  "status": "ok",
  "diagnostics_passed": [],
  "diagnostics_failed": [
    "ljung_box",
    "jarque_bera",
    "arch_lm",
    "cusum",
    "adf",
    "forecast_plausibility"
  ],
  "error_summary": "",
  "rmse_1yr": 177.73550234661786,
  "rmse_3yr": 327.88235428697885,
  "insample_rmse": 376.4118560367088,
  "naive_insample_rmse": 6.6734637289322345,
  "fit_attempts": [
    {
      "attempt": 1,
      "name": "baseline_lbfgs",
      "method": "lbfgs",
      "maxiter": 200,
      "scale_inputs": false,
      "enforce_stationarity": true,
      "status": "warning",
      "optimizer_converged": false,
      "warnings": [
        "Maximum Likelihood optimization failed to converge. Check mle_retvals"
      ]
    },
    {
      "attempt": 2,
      "name": "relaxed_lbfgs",
      "method": "lbfgs",
      "maxiter": 200,
      "scale_inputs": false,
      "enforce_stationarity": false,
      "status": "ok",
      "optimizer_converged": true,
      "warnings": []
    }
  ],
  "fit_strategy": "relaxed_lbfgs",
  "fit_scaled": false,
  "fit_recovered": true
}