{
  "experiment_id": "20260331_threshold_var_full20_300",
  "trial_id": "20260331_threshold_var_full20_300_047",
  "model_class": "Threshold VAR / SETAR",
  "champion_eligible": true,
  "dependency_scope": "econometric",
  "spec": {
    "sample_start": "1995-03-31",
    "target_column": "hpi",
    "target_date_column": "date",
    "champion_eligible": true,
    "description": "Threshold VAR(1) delay=2 q=0.5 threshold=mortgage_rate with mortgage_rate",
    "threshold_var": {
      "lags": 1,
      "trend": "c",
      "delay": 2,
      "threshold_variable": "mortgage_rate",
      "threshold_quantile": 0.5,
      "ridge_alpha": 0.1,
      "endogenous": [
        "hpi",
        "mortgage_rate"
      ],
      "regime_count": 2
    }
  }
}